{
    "boxShadow": "{{appsmith.theme.boxShadow.appBoxShadow}}",
    "borderColor": "#E0DEDE",
    "isVisibleDownload": true,
    "iconSVG": "/static/media/icon.e6911f8bb94dc6c4a102a74740c41763.svg",
    "topRow": 15,
    "isSortable": true,
    "type": "TABLE_WIDGET_V2",
    "inlineEditingSaveOption": "ROW_LEVEL",
    "animateLoading": true,
    "dynamicBindingPathList": [
        {"key": "accentColor"},
        {"key": "borderRadius"},
        {"key": "boxShadow"},
        {"key": "tableData"},
        {"key": "primaryColumns.bundleID.computedValue"},
        {"key": "primaryColumns.description.computedValue"},
        {"key": "primaryColumns.price.computedValue"},
        {"key": "primaryColumns.title.computedValue"},
        {"key": "primaryColumns.type.computedValue"}
    ],
    "needsHeightForContent": true,
    "leftColumn": 7,
    "delimiter": ",",
    "defaultSelectedRowIndex": 0,
    "flexVerticalAlignment": "start",
    "accentColor": "{{appsmith.theme.colors.primaryColor}}",
    "isVisibleFilters": true,
    "isVisible": true,
    "enableClientSideSearch": true,
    "version": 2,
    "totalRecordsCount": 0,
    "tags": [
        "Suggested",
        "Display"
    ],
    "isLoading": false,
    "childStylesheet": {
        "button": {
            "boxShadow": "none",
            "borderRadius": "{{appsmith.theme.borderRadius.appBorderRadius}}",
            "buttonColor": "{{appsmith.theme.colors.primaryColor}}"
        },
        "iconButton": {
            "boxShadow": "none",
            "borderRadius": "{{appsmith.theme.borderRadius.appBorderRadius}}",
            "buttonColor": "{{appsmith.theme.colors.primaryColor}}"
        },
        "menuButton": {
            "boxShadow": "none",
            "borderRadius": "{{appsmith.theme.borderRadius.appBorderRadius}}",
            "menuColor": "{{appsmith.theme.colors.primaryColor}}"
        },
        "editActions": {
            "saveButtonColor": "{{appsmith.theme.colors.primaryColor}}",
            "saveBorderRadius": "{{appsmith.theme.borderRadius.appBorderRadius}}",
            "discardBorderRadius": "{{appsmith.theme.borderRadius.appBorderRadius}}",
            "discardButtonColor": "{{appsmith.theme.colors.primaryColor}}"
        }
    },
    "borderRadius": "{{appsmith.theme.borderRadius.appBorderRadius}}",
    "columnUpdatedAt": 1713477463461,
    "originalBottomRow": 46,
    "defaultSelectedRowIndices": [0],
    "needsErrorInfo": false,
    "mobileBottomRow": 34,
    "widgetName": "bundle_table",
    "defaultPageSize": 0,
    "columnOrder": [
        "bundleID",
        "description",
        "price",
        "title",
        "type"
    ],
    "dynamicPropertyPathList": [{"key": "tableData"}],
    "displayName": "Table",
    "bottomRow": 43,
    "columnWidthMap": {},
    "parentRowSpace": 10,
    "hideCard": false,
    "mobileRightColumn": 46,
    "parentColumnSpace": 11.890625,
    "dynamicTriggerPathList": [],
    "borderWidth": "1",
    "primaryColumns": {
        "price": {
            "computedValue": "{{bundle_table.processedTableData.map((currentRow, currentIndex) => ( currentRow[\"price\"]))}}",
            "isEditable": false,
            "notation": "standard",
            "alias": "price",
            "enableSort": true,
            "isSaveVisible": true,
            "id": "price",
            "isDisabled": false,
            "allowSameOptionsInNewRow": true,
            "validation": {},
            "isCellVisible": true,
            "isDerived": false,
            "textSize": "0.875rem",
            "allowCellWrapping": false,
            "index": 2,
            "isDiscardVisible": true,
            "isVisible": true,
            "label": "price",
            "fontStyle": "",
            "textColor": "",
            "columnType": "number",
            "thousandSeparator": true,
            "horizontalAlignment": "LEFT",
            "isCellEditable": false,
            "decimals": 0,
            "width": 150,
            "enableFilter": true,
            "sticky": "",
            "originalId": "price",
            "currencyCode": "USD",
            "cellBackground": "",
            "verticalAlignment": "CENTER"
        },
        "bundleID": {
            "computedValue": "{{bundle_table.processedTableData.map((currentRow, currentIndex) => ( currentRow[\"bundleID\"]))}}",
            "isEditable": false,
            "notation": "standard",
            "alias": "bundleID",
            "enableSort": true,
            "isSaveVisible": true,
            "id": "bundleID",
            "isDisabled": false,
            "allowSameOptionsInNewRow": true,
            "validation": {},
            "isCellVisible": true,
            "isDerived": false,
            "textSize": "0.875rem",
            "allowCellWrapping": false,
            "index": 0,
            "isDiscardVisible": true,
            "isVisible": true,
            "label": "bundleID",
            "fontStyle": "",
            "textColor": "",
            "columnType": "number",
            "thousandSeparator": true,
            "horizontalAlignment": "LEFT",
            "isCellEditable": false,
            "decimals": 0,
            "width": 150,
            "enableFilter": true,
            "sticky": "",
            "originalId": "bundleID",
            "currencyCode": "USD",
            "cellBackground": "",
            "verticalAlignment": "CENTER"
        },
        "description": {
            "computedValue": "{{bundle_table.processedTableData.map((currentRow, currentIndex) => ( currentRow[\"description\"]))}}",
            "isEditable": false,
            "notation": "standard",
            "alias": "description",
            "enableSort": true,
            "isSaveVisible": true,
            "id": "description",
            "isDisabled": false,
            "allowSameOptionsInNewRow": true,
            "validation": {},
            "isCellVisible": true,
            "isDerived": false,
            "textSize": "0.875rem",
            "allowCellWrapping": false,
            "index": 1,
            "isDiscardVisible": true,
            "isVisible": true,
            "label": "description",
            "fontStyle": "",
            "textColor": "",
            "columnType": "text",
            "thousandSeparator": true,
            "horizontalAlignment": "LEFT",
            "isCellEditable": false,
            "decimals": 0,
            "width": 150,
            "enableFilter": true,
            "sticky": "",
            "originalId": "description",
            "currencyCode": "USD",
            "cellBackground": "",
            "verticalAlignment": "CENTER"
        },
        "title": {
            "computedValue": "{{bundle_table.processedTableData.map((currentRow, currentIndex) => ( currentRow[\"title\"]))}}",
            "isEditable": false,
            "notation": "standard",
            "alias": "title",
            "enableSort": true,
            "isSaveVisible": true,
            "id": "title",
            "isDisabled": false,
            "allowSameOptionsInNewRow": true,
            "validation": {},
            "isCellVisible": true,
            "isDerived": false,
            "textSize": "0.875rem",
            "allowCellWrapping": false,
            "index": 3,
            "isDiscardVisible": true,
            "isVisible": true,
            "label": "title",
            "fontStyle": "",
            "textColor": "",
            "columnType": "text",
            "thousandSeparator": true,
            "horizontalAlignment": "LEFT",
            "isCellEditable": false,
            "decimals": 0,
            "width": 150,
            "enableFilter": true,
            "sticky": "",
            "originalId": "title",
            "currencyCode": "USD",
            "cellBackground": "",
            "verticalAlignment": "CENTER"
        },
        "type": {
            "computedValue": "{{bundle_table.processedTableData.map((currentRow, currentIndex) => ( currentRow[\"type\"]))}}",
            "isEditable": false,
            "notation": "standard",
            "alias": "type",
            "enableSort": true,
            "isSaveVisible": true,
            "id": "type",
            "isDisabled": false,
            "allowSameOptionsInNewRow": true,
            "validation": {},
            "isCellVisible": true,
            "isDerived": false,
            "textSize": "0.875rem",
            "allowCellWrapping": false,
            "index": 4,
            "isDiscardVisible": true,
            "isVisible": true,
            "label": "type",
            "fontStyle": "",
            "textColor": "",
            "columnType": "text",
            "thousandSeparator": true,
            "horizontalAlignment": "LEFT",
            "isCellEditable": false,
            "decimals": 0,
            "width": 150,
            "enableFilter": true,
            "sticky": "",
            "originalId": "type",
            "currencyCode": "USD",
            "cellBackground": "",
            "verticalAlignment": "CENTER"
        }
    },
    "key": "jvyultymbu",
    "canFreezeColumn": true,
    "isDeprecated": false,
    "rightColumn": 54,
    "textSize": "0.875rem",
    "widgetId": "7opb6rpzw3",
    "minWidth": 450,
    "tableData": "{{get_bundle_info.data}}",
    "label": "Data",
    "searchKey": "",
    "parentId": "0",
    "renderMode": "CANVAS",
    "mobileTopRow": 6,
    "horizontalAlignment": "LEFT",
    "isVisibleSearch": true,
    "responsiveBehavior": "fill",
    "originalTopRow": 18,
    "mobileLeftColumn": 12,
    "isVisiblePagination": true,
    "verticalAlignment": "CENTER"
}