{
    "needsErrorInfo": false,
    "mobileBottomRow": 237,
    "widgetName": "Text1",
    "displayName": "Text",
    "iconSVG": "/static/media/icon.a47d6d5dbbb718c4dc4b2eb4f218c1b7.svg",
    "searchTags": [
        "typography",
        "paragraph",
        "label"
    ],
    "topRow": 229,
    "bottomRow": 234,
    "parentRowSpace": 10,
    "type": "TEXT_WIDGET",
    "hideCard": false,
    "mobileRightColumn": 38,
    "animateLoading": true,
    "overflow": "NONE",
    "fontFamily": "{{appsmith.theme.fontFamily.appFont}}",
    "parentColumnSpace": 11.890625,
    "dynamicTriggerPathList": [],
    "leftColumn": 14,
    "dynamicBindingPathList": [
        {"key": "truncateButtonColor"},
        {"key": "fontFamily"},
        {"key": "borderRadius"}
    ],
    "shouldTruncate": false,
    "truncateButtonColor": "{{appsmith.theme.colors.primaryColor}}",
    "text": "View and create experiences",
    "key": "8he51wcaou",
    "isDeprecated": false,
    "rightColumn": 53,
    "textAlign": "LEFT",
    "dynamicHeight": "AUTO_HEIGHT",
    "widgetId": "x38xj3bt2l",
    "minWidth": 450,
    "isVisible": true,
    "fontStyle": "BOLD",
    "textColor": "#231F20",
    "version": 1,
    "parentId": "0",
    "tags": [
        "Suggested",
        "Content"
    ],
    "renderMode": "CANVAS",
    "isLoading": false,
    "mobileTopRow": 233,
    "responsiveBehavior": "fill",
    "originalTopRow": 236,
    "borderRadius": "{{appsmith.theme.borderRadius.appBorderRadius}}",
    "mobileLeftColumn": 22,
    "maxDynamicHeight": 9000,
    "originalBottomRow": 241,
    "fontSize": "1.875rem",
    "minDynamicHeight": 4
}